pyDoodle2Web/__init__.py
pyDoodle2Web/dynamic_generator.py
pyDoodle2Web/htmlGenerator.py
pyDoodle2Web/ocr.py
pyDoodle2Web/pyDoodle2Web.py
pyDoodle2Web/components/__init__.py
pyDoodle2Web/components/card/__init__.py
pyDoodle2Web/components/card/card.py
pyDoodle2Web/components/carousel/__init__.py
pyDoodle2Web/components/carousel/carousel.py
pyDoodle2Web/components/coloumn/__init__.py
pyDoodle2Web/components/coloumn/coloumn.py
pyDoodle2Web/components/container/__init__.py
pyDoodle2Web/components/container/container.py
pyDoodle2Web/components/footer/__init__.py
pyDoodle2Web/components/footer/footer.py
pyDoodle2Web/components/html/__init__.py
pyDoodle2Web/components/html/html.py
pyDoodle2Web/components/image/__init__.py
pyDoodle2Web/components/image/image.py
pyDoodle2Web/components/jumbotron/__init__.py
pyDoodle2Web/components/jumbotron/jumbotron.py
pyDoodle2Web/components/navbar/__init__.py
pyDoodle2Web/components/navbar/navbar.py
pyDoodle2Web/components/row/__init__.py
pyDoodle2Web/components/row/row.py
pyDoodle2Web/components/text/__init__.py
pyDoodle2Web/components/text/text.py
pyDoodle2Web-0.0.7.dist-info/LICENSE
pyDoodle2Web-0.0.7.dist-info/METADATA
pyDoodle2Web-0.0.7.dist-info/WHEEL
pyDoodle2Web-0.0.7.dist-info/top_level.txt
pyDoodle2Web-0.0.7.dist-info/RECORD
