Metadata-Version: 2.1
Name: pyDoodle2Web
Version: 0.0.7
Summary: UNKNOWN
Home-page: https://github.com/pyDoodle2Web/pyDoodle2Web
Author: pyDoodle2Web
Author-email: renerjake@gmail.com
License: UNKNOWN
Keywords: bootstrap,ocr,website,genertion
Platform: UNKNOWN
Classifier: Programming Language :: Python :: 3
Classifier: License :: OSI Approved :: MIT License
Classifier: Operating System :: OS Independent
Requires-Python: >=3.6
Requires-Dist: beautifulsoup4
Requires-Dist: pytesseract
